{
  "version": "1.0.0",
  "minimum_cell_size": 500,
  "dimensions": [
    {
      "name": "platform",
      "predeclared": true,
      "decision_use": "diagnostic_supporting",
      "metrics": [
        "activation_rate_7d",
        "support_ticket_rate_7d"
      ]
    },
    {
      "name": "acquisition_channel",
      "predeclared": true,
      "decision_use": "diagnostic_supporting",
      "metrics": [
        "activation_rate_7d",
        "support_ticket_rate_7d"
      ]
    },
    {
      "name": "country",
      "predeclared": false,
      "decision_use": "exploratory_only",
      "metrics": [
        "activation_rate_7d"
      ]
    }
  ]
}
