{
  "questions": [
    {
      "id": "pre-source-purpose",
      "stage": "pre",
      "question": "Зачем объявлять raw-таблицы как dbt sources вместо прямого `select * from raw.raw_orders`?",
      "options": [
        "Чтобы dbt видел lineage, мог выбирать downstream models, документировать источник и считать freshness.",
        "Чтобы dbt автоматически исправлял все плохие значения в raw-таблице.",
        "Чтобы raw-таблица стала mart-моделью.",
        "Чтобы больше не нужен был `dbt_project.yml`."
      ],
      "correct": 0,
      "explanation": "`source()` делает raw dependency видимой для manifest, docs, selection и source freshness; качество данных все равно нужно проверять отдельно."
    },
    {
      "id": "pre-ref-purpose",
      "stage": "pre",
      "question": "Что делает `ref('stg_orders')` в модели `int_order_line_revenue`?",
      "options": [
        "Создает dependency между моделями и компилируется в полное имя relation для текущего target.",
        "Выполняет Python import из файла `stg_orders.py`.",
        "Заменяет data tests для `stg_orders`.",
        "Сохраняет результат модели как CSV."
      ],
      "correct": 0,
      "explanation": "`ref()` одновременно дает переносимое имя relation и сообщает dbt порядок зависимостей в graph."
    },
    {
      "id": "post-staging-boundary",
      "stage": "post",
      "question": "Почему в этом уроке только staging models читают `source()`, а intermediate/mart models читают `ref()`?",
      "options": [
        "Потому что staging является границей нормализации raw, а downstream слои должны зависеть от проверенных моделей графа.",
        "Потому что `source()` технически запрещен в mart SQL.",
        "Потому что `ref()` можно использовать только в mart-слое.",
        "Потому что source freshness работает только для staging views."
      ],
      "correct": 0,
      "explanation": "Это архитектурное правило фазы: raw boundary видна в staging, а downstream логика должна проходить через ref graph."
    },
    {
      "id": "post-freshness",
      "stage": "post",
      "question": "Что проверяет `dbt source freshness`?",
      "options": [
        "Максимальный loaded_at timestamp source table против настроенных warn/error thresholds.",
        "Уникальность primary key в mart-модели.",
        "Стиль SQL по правилам SQLFluff.",
        "Полноту описаний колонок в docs site."
      ],
      "correct": 0,
      "explanation": "Freshness использует `loaded_at_field` или аналогичную настройку источника и сравнивает свежесть с SLA-порогами."
    },
    {
      "id": "post-direct-raw",
      "stage": "post",
      "question": "Что плохого в hardcoded `raw.raw_orders` внутри mart SQL?",
      "options": [
        "dbt manifest не увидит source dependency, нормализация staging будет обойдена, а порядок сборки и lineage станут неполными.",
        "DuckDB перестанет читать таблицу.",
        "Такой SQL всегда медленнее `ref()`.",
        "Это допустимо, если добавить комментарий над запросом."
      ],
      "correct": 0,
      "explanation": "Direct raw reference может технически выполниться, но ломает управляемость dbt graph и скрывает контракт источника."
    }
  ]
}
