{
  "questions": [
    {
      "id": "pre-1",
      "stage": "pre",
      "question": "Какова cardinality orders к order_items?",
      "options": ["one-to-one", "one-to-many", "many-to-one", "нет связи"],
      "correct": 1,
      "explanation": "Один заказ может содержать несколько товарных позиций."
    },
    {
      "id": "pre-2",
      "stage": "pre",
      "question": "Почему сумма orders.amount после join с items опасна?",
      "options": ["amount меняет dtype", "Сумма заказа повторяется для каждой позиции", "Join удаляет валюту", "Index становится строкой"],
      "correct": 1,
      "explanation": "Detail-строки размножают значения таблицы более крупного grain."
    },
    {
      "id": "post-1",
      "stage": "post",
      "question": "Как сохранить grain заказа при добавлении item_total?",
      "options": ["Сначала агрегировать items по order_id", "Использовать outer без ключа", "Удалить amount", "Сбросить индекс"],
      "correct": 0,
      "explanation": "После агрегации обе стороны имеют одну строку на order_id."
    },
    {
      "id": "post-2",
      "stage": "post",
      "question": "Что проверяет validate='many_to_one'?",
      "options": ["Уникальность ключа справа", "Уникальность ключа слева", "Отсутствие пропусков во всех столбцах", "Сортировку"],
      "correct": 0,
      "explanation": "Много строк слева могут ссылаться на одну уникальную строку справа."
    },
    {
      "id": "post-3",
      "stage": "post",
      "question": "Зачем нужен indicator?",
      "options": ["Для ускорения", "Чтобы видеть matched и unmatched происхождение строк", "Для переименования ключа", "Для groupby"],
      "correct": 1,
      "explanation": "Индикатор делает покрытие ключей частью отчёта объединения."
    }
  ]
}
