{
  "questions": [
    {
      "id": "pre-1",
      "stage": "pre",
      "question": "Что определяет dtype массива?",
      "options": [
        "Только число осей",
        "Представление и диапазон каждого элемента",
        "Имена строк",
        "Порядок сортировки"
      ],
      "correct": 1,
      "explanation": "dtype задаёт формат элемента в памяти, его диапазон и точность."
    },
    {
      "id": "pre-2",
      "stage": "pre",
      "question": "Сколько памяти занимают 1000 элементов dtype uint8 без учёта объекта массива?",
      "options": [
        "1000 байт",
        "8000 байт",
        "8 байт",
        "Зависит только от shape"
      ],
      "correct": 0,
      "explanation": "uint8 занимает один байт на элемент, поэтому nbytes равен 1000."
    },
    {
      "id": "post-1",
      "stage": "post",
      "question": "Каков диапазон uint8?",
      "options": [
        "-128..127",
        "0..255",
        "0..256",
        "-255..255"
      ],
      "correct": 1,
      "explanation": "Восемь беззнаковых битов кодируют 2^8 значений от 0 до 255."
    },
    {
      "id": "post-2",
      "stage": "post",
      "question": "Почему массив [1, NaN, 3] нельзя хранить в обычном integer dtype NumPy?",
      "options": [
        "Integer-массивы одномерные",
        "NaN является специальным значением с плавающей точкой",
        "Число 3 слишком велико",
        "NumPy запрещает пропуски"
      ],
      "correct": 1,
      "explanation": "Обычные целочисленные dtype не имеют отдельного представления NaN."
    },
    {
      "id": "post-3",
      "stage": "post",
      "question": "Когда уменьшение float64 до float32 требует проверки?",
      "options": [
        "Никогда, значения полностью эквивалентны",
        "Только при одном элементе",
        "Когда допустимая точность расчёта может быть потеряна",
        "Только если shape квадратный"
      ],
      "correct": 2,
      "explanation": "float32 имеет меньшую точность и диапазон, поэтому выбор зависит от допуска задачи."
    }
  ]
}
