{
  "title": "Контракт и аудит данных",
  "type": "case",
  "tracks": ["core", "product", "data", "decision", "ml", "delivery"],
  "prerequisites": ["18-capstones/01-problem-selection"],
  "time_minutes": 360,
  "outcome": "Фиксирует dataset manifest, grain, keys, lineage, временные границы, license/privacy policy и маршрутные leakage/quality checks до реализации метода.",
  "artifact": {
    "name": "capstone-data-contract-auditor",
    "type": "cli",
    "path": "outputs/capstone_data_contract_auditor.py"
  }
}
