{
  "allowed_response_statuses": [
    "accepted",
    "declined_with_evidence",
    "partially_accepted"
  ],
  "allowed_reviewer_types": [
    "independent_agent",
    "learner_peer",
    "mentor"
  ],
  "allowed_severities": [
    "blocker",
    "major",
    "minor",
    "question"
  ],
  "change_check_map": {
    "reviewed_claims.json#claim_id=claim-baseline": [
      "sensitivity_analysis",
      "claim_evidence_audit"
    ],
    "reviewed_claims.json#claim_id=claim-clean-room": [
      "clean_room_rerun_summary",
      "claim_evidence_audit"
    ],
    "reviewed_claims.json#claim_id=claim-sensitivity": [
      "sensitivity_analysis",
      "claim_evidence_audit"
    ]
  },
  "project_id": "weekly-retention-decision-core",
  "required_self_review_checks": [
    "decision_and_claim_boundary",
    "data_rights_and_privacy",
    "baseline_and_method",
    "verification_and_failure_modes",
    "handoff_and_limitations"
  ],
  "rerun_checks": {
    "claim_evidence_audit": "Re-check exact evidence and limitations for reviewed claims.",
    "clean_room_rerun_summary": "Re-check what clean-room evidence does and does not prove.",
    "sensitivity_analysis": "Re-evaluate the frozen decision and every predeclared flip."
  },
  "review_id": "weekly-retention-core-review-v1",
  "rubric_dimensions": [
    "problem_framing",
    "data_contract",
    "method_and_baseline",
    "verification",
    "delivery_and_handoff",
    "review_and_defense"
  ],
  "verification_id": "weekly-retention-core-verification-v1",
  "version": "1.0.0"
}
