{
  "leakage_audit_id": "active-subscriptions-temporal-leakage",
  "forecast_id": "active-subscriptions-4w-capacity",
  "target_metric": "active_subscriptions",
  "target_segments": [
    "all",
    "android"
  ],
  "timezone": "Europe/Moscow",
  "frequency": "D",
  "forecast_origin": "2026-03-18T09:00:00+03:00",
  "training_start": "2026-03-02",
  "training_end": "2026-03-16",
  "first_forecast_date": "2026-03-18",
  "horizon_end": "2026-04-14",
  "horizon_days": 28,
  "embargo_dates": [
    "2026-03-17"
  ],
  "split_type": "time_ordered_cutoff",
  "revision_policy": "exclude_revisions_after_forecast_origin",
  "selected_features": [
    "value_lag_1",
    "rolling_7_mean_lag1",
    "day_of_week",
    "campaign_active"
  ],
  "rejected_feature_candidates": 6
}
